sphinxcontrib/btn/__init__.py
sphinxcontrib/btn/btn.py
sphinx_btn-0.1.2.dist-info/LICENSE
sphinx_btn-0.1.2.dist-info/METADATA
sphinx_btn-0.1.2.dist-info/WHEEL
sphinx_btn-0.1.2.dist-info/top_level.txt
sphinx_btn-0.1.2.dist-info/RECORD
