Metadata-Version: 2.1
Name: sphinx-btn
Version: 0.1.2
Summary: A sphinx custom role to embed inline btn which is an icon in a guilabel in the latex and html outputs
Author-email: Pierrick Rambaud <pierrick.rambaud49@gmail.com>
License: BSD 2-Clause
Project-URL: repository, https://github.com/sphinx-contrib/btn
Keywords: python,fontawesome,sphinx,extention
Classifier: Development Status :: 5 - Production/Stable
Classifier: Framework :: Sphinx :: Extension
Classifier: Intended Audience :: Developers
Classifier: Topic :: Software Development :: Build Tools
Classifier: License :: OSI Approved :: BSD License
Classifier: Programming Language :: Python
Classifier: Programming Language :: Python :: 3
Classifier: Programming Language :: Python :: 3.7
Classifier: Programming Language :: Python :: 3.8
Classifier: Programming Language :: Python :: 3.9
Classifier: Programming Language :: Python :: 3.10
Classifier: Topic :: Documentation
Classifier: Topic :: Utilities
Requires-Python: >=3.6.9
License-File: LICENSE
Requires-Dist: sphinx
Requires-Dist: sphinx-icon (>=0.2.2)
Provides-Extra: dev
Requires-Dist: nox ; extra == 'dev'
Requires-Dist: pre-commit ; extra == 'dev'
Requires-Dist: mypy ; extra == 'dev'
Provides-Extra: doc
Requires-Dist: pydata-sphinx-theme (==0.13.0rc3) ; extra == 'doc'
Requires-Dist: sphinx-design ; extra == 'doc'
Requires-Dist: sphinx-copybutton ; extra == 'doc'
Provides-Extra: test
Requires-Dist: pytest ; extra == 'test'
Requires-Dist: beautifulsoup4 ; extra == 'test'
Requires-Dist: pytest-regressions ; extra == 'test'
Requires-Dist: pytest-cov ; extra == 'test'
